xminds/__init__.py
xminds/compat.py
xminds/_lib/__init__.py
xminds/_lib/compat.py
xminds/_lib/hashmap.py
xminds/api/__init__.py
xminds/api/apirequest.py
xminds/api/client.py
xminds/api/exceptions.py
xminds/ds/__init__.py
xminds/ds/scaling.py
xminds/lib/__init__.py
xminds/lib/aggregate.py
xminds/lib/arraybase.py
xminds/lib/arrays.py
xminds/lib/iterable.py
xminds/lib/utils.py
xminds-0.1.1.dist-info/METADATA
xminds-0.1.1.dist-info/WHEEL
xminds-0.1.1.dist-info/top_level.txt
xminds-0.1.1.dist-info/RECORD
