Metadata-Version: 2.1
Name: xminds
Version: 0.1.1
Summary: Crossing Minds data science python library and API client
Home-page: https://github.com/Crossing-Minds/xminds-python
Author: Crossing Minds, Inc
Author-email: contact@crossingminds.com
License: UNKNOWN
Platform: UNKNOWN
Classifier: Programming Language :: Python :: 3
Classifier: License :: OSI Approved :: MIT License
Classifier: Operating System :: OS Independent
Requires-Python: >=3.6
Requires-Dist: requests (>=2.19.1)
Requires-Dist: numpy (>=1.16)
